.gitignore
.gitmodules
.travis.yml
CHANGES.rst
CONTRIBUTORS.rst
Makefile
README.rst
TODO.rst
base.cfg
bootstrap.py
buildout.cfg
plone-4.3.x.cfg
plone-5.0.x.cfg
plone-5.1.x.cfg
requirements.txt
setup.cfg
setup.py
travis.cfg
docs/LICENSE.GPL
docs/LICENSE.txt
docs/screenshot.png
src/collective/__init__.py
src/collective.shibboleth.egg-info/PKG-INFO
src/collective.shibboleth.egg-info/SOURCES.txt
src/collective.shibboleth.egg-info/dependency_links.txt
src/collective.shibboleth.egg-info/entry_points.txt
src/collective.shibboleth.egg-info/namespace_packages.txt
src/collective.shibboleth.egg-info/not-zip-safe
src/collective.shibboleth.egg-info/requires.txt
src/collective.shibboleth.egg-info/top_level.txt
src/collective/shibboleth/__init__.py
src/collective/shibboleth/auth.py
src/collective/shibboleth/configure.zcml
src/collective/shibboleth/setuphandlers.py
src/collective/shibboleth/testing.py
src/collective/shibboleth/upgrades.py
src/collective/shibboleth/utils.py
src/collective/shibboleth/browser/__init__.py
src/collective/shibboleth/browser/configure.zcml
src/collective/shibboleth/browser/shibboleth-ds/blank.gif
src/collective/shibboleth/browser/shibboleth-ds/idpselect.css
src/collective/shibboleth/browser/shibboleth-ds/idpselect.js
src/collective/shibboleth/browser/shibboleth-ds/idpselect_config.js
src/collective/shibboleth/browser/shibboleth-ds/nonminimised/idpselect.js
src/collective/shibboleth/browser/shibboleth-ds/nonminimised/idpselect_config.js
src/collective/shibboleth/browser/shibboleth-ds/nonminimised/idpselect_languages.js
src/collective/shibboleth/browser/shibboleth-ds/nonminimised/json2.js
src/collective/shibboleth/browser/shibboleth-ds/nonminimised/typeahead.js
src/collective/shibboleth/locales/en/LC_MESSAGES/plone.po
src/collective/shibboleth/portlets/__init__.py
src/collective/shibboleth/portlets/configure.zcml
src/collective/shibboleth/portlets/shibbolethloginportlet.pt
src/collective/shibboleth/portlets/shibbolethloginportlet.py
src/collective/shibboleth/profiles/default/actions.xml
src/collective/shibboleth/profiles/default/collective.shibboleth_various.txt
src/collective/shibboleth/profiles/default/metadata.xml
src/collective/shibboleth/profiles/default/portlets.xml
src/collective/shibboleth/profiles/default/rolemap.xml
src/collective/shibboleth/tests/__init__.py
src/collective/shibboleth/tests/base_shibbolethloginportlet.py
